xjd/__about__.py
xjd/__init__.py
xjd-0.0.1.dist-info/METADATA
xjd-0.0.1.dist-info/WHEEL
xjd-0.0.1.dist-info/licenses/LICENSE.txt
xjd-0.0.1.dist-info/RECORD
